{
    "package": {
        "util": [
            {
                "id": "947514445C3F4582BFFA8E38A6E5B6B4",
                "tag": "util",
                "type": "apt",
                "name": "curl",
                "url": null,
                "file": null
            }
        ],
        "dev": [
            {
                "id": "7298E7711B5D48DE88F9E9DC02E2B458",
                "tag": "dev",
                "type": "snap",
                "name": "postman",
                "url": null,
                "file": null
            },
            {
                "id": "BB9C3497D4134FFFAB81A8CF547AC117",
                "tag": "dev",
                "type": "snap",
                "name": "docker",
                "url": null,
                "file": null
            },
            {
                "id": "0EB8B513FB4D4EF9950B35873536473F",
                "tag": "dev",
                "type": "apt-get",
                "name": "git",
                "url": null,
                "file": null
            }
        ],
        "music": [
            {
                "id": "D60B10B107C2415C8E0F91CC8C2DB5C1",
                "tag": "music",
                "type": "snap",
                "name": "spotify",
                "url": null,
                "file": null
            }
        ],
        "social": [
            {
                "id": "0BD32ECDB98444C3A8E5CB09891BB584",
                "tag": "social",
                "type": "snap",
                "name": "discord",
                "url": null,
                "file": null
            }
        ],
        "python": [
            {
                "id": "9E1CCB766EEC4709A7CAC4F81B15420A",
                "tag": "python",
                "type": "apt-get",
                "name": "python-pip",
                "url": null,
                "file": null
            },
            {
                "id": "7F7934AEA6094A56ACFFCDE44113FAAF",
                "tag": "python",
                "type": "apt",
                "name": "pep8",
                "url": null,
                "file": null
            },
            {
                "id": "0CAC3E0DBA7E44A99000D82CF05DF9FF",
                "tag": "python",
                "type": "apt",
                "name": "build-essential",
                "url": null,
                "file": null
            }
           
        ],
        "pip": [
            {
                "id": "593E7B28B7B5474A80737A5BA1447FC9",
                "tag": "pip",
                "type": "pip",
                "name": "IPython",
                "url": null,
                "file": null
            }
        ]
    },
    "alias": {
        "python": [
            {
                "id": "6E19701F9D3246B6A3B2AE99692DE819",
                "tag": "python",
                "command": "ipython",
                "body": "python -c 'from IPython import embed; embed()'",
                "type": "exec"
            }
        ],
        "django": [
            {
                "id": "22A99CDF304B4A6A97FF7354476190B7",
                "tag": "django",
                "command": "runserver",
                "body": "python manage.py runserver",
                "type": "exec"
            }
        ],
        "git": [
            {
                "id": "BD3F63052FE0492B89D55E2B63F130EE",
                "tag": "git",
                "command": "gitname",
                "body": "git config --global user.name",
                "type": "exec"
            },
            {
                "id": "65780977FA8443F38FCA18EBDE56A757",
                "tag": "git",
                "command": "gitemail",
                "body": "git config --global user.email",
                "type": "exec"
            }
        ],
        "util": [
            {
                "id": "1F540CE01C9B43C48327D2200404AD58",
                "tag": "util",
                "command": "profile",
                "body": "google-chrome ~/.config/linuxp/linux_profile.json",
                "type": "exec"
            }
        ]
    },
    "script": {
        "dev": [
            {
                "id": "DC7EC742C7BA4AD5AE0A393AB6398A8B",
                "tag": "dev",
                "type": "shell",
                "name": "install_asdf",
                "shebang": null,
                "body": [
                    "sudo apt install curl git",
                    "git clone https://github.com/asdf-vm/asdf.git ~/.asdf --branch v0.10.2",
                    "echo '. $HOME/.asdf/asdf.sh' >> ~/.bashrc",
                    "echo '. $HOME/.asdf/completions/asdf.bash' >> ~/.bashrc"
                ]
            }
        ]
    }
}
